reagan/__init__.py
reagan/dcm.py
reagan/drive.py
reagan/dv360.py
reagan/fidelity.py
reagan/gcp.py
reagan/ihub.py
reagan/psql.py
reagan/sa360.py
reagan/smartsheets.py
reagan/sqlserver.py
reagan/subclass.py
reagan-2.3.0.dist-info/LICENSE
reagan-2.3.0.dist-info/METADATA
reagan-2.3.0.dist-info/WHEEL
reagan-2.3.0.dist-info/top_level.txt
reagan-2.3.0.dist-info/RECORD
