Metadata-Version: 2.1
Name: reagan
Version: 2.3.0
Summary: Package for streamlining credentials, connections, and data flow
Home-page: https://github.com/schustda/reagan
Author: Douglas Schuster
Author-email: douglas.schuster@carat.com
License: UNKNOWN
Platform: UNKNOWN
Requires-Dist: msrest (==0.6.11)
Requires-Dist: pyodbc (==4.0.30)
Requires-Dist: pandas (==0.25.3)
Requires-Dist: numpy (>=1.16.6)
Requires-Dist: boto3 (==1.19.4)
Requires-Dist: botocore (==1.22.4)
Requires-Dist: smartsheet-python-sdk (==2.68.3)
Requires-Dist: retrying (==1.3.3)
Requires-Dist: psycopg2 (==2.9.1)
Requires-Dist: SQLAlchemy (>=1.3.18)
Requires-Dist: requests (>=2.24.0)
Requires-Dist: textblob (==0.15.3)
Requires-Dist: beautifulsoup4 (==4.9.1)
Requires-Dist: google-api-python-client (==1.10.0)
Requires-Dist: protobuf (==3.13.0)
Requires-Dist: azure-devops (==6.0.0b2)
